storekit/__init__.py
storekit/exceptions.py
storekit/jws.py
storekit/models.py
storekit/app_store_receipts/__init__.py
storekit/app_store_receipts/client.py
storekit/app_store_receipts/exceptions.py
storekit/app_store_receipts/verify_receipt_response.py
storekit/app_store_server_api/__init__.py
storekit/app_store_server_api/client.py
storekit/app_store_server_api/exceptions.py
storekit/app_store_server_api/history_response.py
storekit/app_store_server_api/order_look_up_response.py
storekit/app_store_server_api/status_response.py
storekit/app_store_server_api/transaction_info_response.py
storekit/app_store_server_notifications/__init__.py
storekit/app_store_server_notifications/response_body.py
storekit/utils/__init__.py
storekit/utils/enum.py
storekit_python-0.0.2.dist-info/METADATA
storekit_python-0.0.2.dist-info/WHEEL
storekit_python-0.0.2.dist-info/licenses/LICENSE
storekit_python-0.0.2.dist-info/RECORD
