Metadata-Version: 2.1
Name: storekit-python
Version: 0.0.2
Summary: The Storekit Python library provides support for in-app purchases and interactions with the App Store.
Author-email: crowser <xuwendi@xiachufang.com>
License: MIT
License-File: LICENSE
Classifier: Programming Language :: Python :: 3
Classifier: Programming Language :: Python :: 3.7
Classifier: Programming Language :: Python :: 3.8
Classifier: Programming Language :: Python :: 3.9
Classifier: Programming Language :: Python :: 3.10
Classifier: Programming Language :: Python :: 3.11
Requires-Python: >=3.7
Requires-Dist: cryptography>=38.0.0
Requires-Dist: pydantic>=1.9.0
Requires-Dist: pyjwt>=2.6.0
Requires-Dist: requests>=2.12.0
